promail_template/__init__.py
promail_template/template.py
promail_template/templates/__init__.py
promail_template/templates/body/__init__.py
promail_template/templates/footer/__init__.py
promail_template/templates/full/__init__.py
promail_template/templates/full/hello_world/__init__.py
promail_template/templates/full/hello_world/sample.json
promail_template/templates/full/hello_world/schema.json
promail_template/templates/full/hello_world/template.mjml
promail_template/templates/full/hello_world/template.py
promail_template/templates/full/image_description_table/__init__.py
promail_template/templates/full/image_description_table/sample.json
promail_template/templates/full/image_description_table/schema.json
promail_template/templates/full/image_description_table/template.mjml
promail_template/templates/full/image_description_table/template.py
promail_template/templates/header/__init__.py
promail_template/utilities/__init__.py
promail_template/utilities/schema_generation.py
promail_template-0.3.0.dist-info/entry_points.txt
promail_template-0.3.0.dist-info/LICENSE
promail_template-0.3.0.dist-info/WHEEL
promail_template-0.3.0.dist-info/METADATA
promail_template-0.3.0.dist-info/RECORD
