Metadata-Version: 2.1
Name: promail-template
Version: 0.3.0
Summary: Promail Template Libary
Author: Antoine Wood
Author-email: antoinewood@gmail.com
Requires-Python: >=3.8,<4.0
Classifier: Programming Language :: Python :: 3
Classifier: Programming Language :: Python :: 3.10
Classifier: Programming Language :: Python :: 3.8
Classifier: Programming Language :: Python :: 3.9
Requires-Dist: Jinja2 (>=3.1.2,<4.0.0)
Requires-Dist: click (>=8.1.3,<9.0.0)
Requires-Dist: genson (>=1.2.2,<2.0.0)
Requires-Dist: html2text (==2020.1.16)
Requires-Dist: jsonschema (>=4.5.1,<5.0.0)
Requires-Dist: mjml (>=0.7.0,<0.8.0)
Requires-Dist: nox (>=2022.1.7,<2023.0.0)
Requires-Dist: requests (>=2.27.1,<3.0.0)
